Workbook

Sheet Contacts
A1: Household Name | B1: Individual Names | C1: Relationship | D1: Relationship Tier | E1: Address Line 1 | F1: Address Line 2 | G1: City | H1: State | I1: ZIP | J1: Country | K1: Address Status | L1: Primary Phone | M1: Secondary Phone | N1: Primary Email | O1: Secondary Email | P1: Instagram | Q1: Facebook | R1: LinkedIn | S1: Twitter/X | T1: Other Social | U1: Preferred Contact | V1: Year Added | W1: Card Type Pref | X1: 2024 Sent | Y1: 2024 Response | Z1: Gift Exchange? | AA1: Gift Occasion | AB1: Gift Budget Tier | AC1: 2024 Gift Given | AD1: 2024 Gift Value | AE1: 2024 Gift Received | AF1: 2024 Gift Recv Value | AG1: Gift Notes | AH1: Birthdays | AI1: Anniversary | AJ1: Kids/Pets | AK1: Notes | AL1: Last Contact Date | AM1: Annual Touchpoints Target | AN1: 2024 Touchpoints | AO1: Reciprocity | AP1: Relationship Trend
A2: Mom & Dad | B2: Mom, Dad | C2: Family | D2: Inner Circle | E2: 27 Tanglewood Dr | G2: Attleboro | H2: MA | J2: USA | K2: Verified | V2: 2024
A3: Trini & Dylan | B3: Trini, Dylan | C3: Family | D3: Inner Circle | E3: 10 Donato Dr | G3: Franklin | H3: MA | J3: USA | K3: Needs Confirmation | V3: 2024
A4: Elliot | B4: Elliot | C4: Family | D4: Inner Circle | E4: 10 Donato Dr | G4: Franklin | H4: MA | J4: USA | K4: Needs Confirmation | V4: 2024
A5: Cassie & Brent & Theo | B5: Cassie, Brent, Theo | C5: Family | D5: Inner Circle | E5: 10 Donato Dr | G5: Franklin | H5: MA | J5: USA | K5: Needs Confirmation | V5: 2024
A6: Emma | B6: Emma | C6: Family | D6: Inner Circle | E6: 10 Donato Dr | G6: Franklin | H6: MA | J6: USA | K6: Needs Confirmation | V6: 2024
A7: Aunt Pam & Uncle John | B7: Pam, John | C7: Family | D7: Close | E7: 14 Wildcat Ln | G7: Plymouth | H7: MA | J7: USA | K7: Verified | V7: 2024
A8: Aunt Sandy & Uncle Howie | B8: Sandy, Howie | C8: Family | D8: Close | H8: MA | J8: USA | K8: Needs Lookup | V8: 2024
A9: Aunt Jan & Uncle Bud | B9: Jan, Bud | C9: Family | D9: Close | H9: MA | J9: USA | K9: Needs Lookup | V9: 2024
A10: Fran | B10: Fran | C10: Family | D10: Close | J10: USA | K10: Needs Lookup | V10: 2024
A11: Kyle & Jeannette | B11: Kyle, Jeannette | C11: Family | D11: Close | J11: USA | K11: Needs Lookup | V11: 2024
A12: Carol | B12: Carol | C12: Family | D12: Close | J12: USA | K12: Needs Lookup | V12: 2024
A13: Lauren & Rob | B13: Lauren, Rob | C13: Family | D13: Close | E13: 260 Cliff Dr | G13: North Attleboro | H13: MA | J13: USA | K13: Verified | V13: 2024
A14: Mel | B14: Mel | C14: Family | D14: Close | J14: USA | K14: Needs Lookup | V14: 2024
A15: Dan & Chelsea | B15: Dan, Chelsea | C15: Friend | D15: Close | E15: 251 Old River Rd | G15: Lincoln | H15: RI | J15: USA | K15: Verified | V15: 2024
A16: Brian & Carly | B16: Brian, Carly | C16: Friend | D16: Close | J16: USA | K16: Needs Lookup | V16: 2024
A17: Derek & Christine | B17: Derek, Christine | C17: Friend | D17: Close | E17: 14 Lindy Ave | G17: Riverside | H17: RI | J17: USA | K17: Verified | V17: 2024
A18: Norm & Judy | B18: Norm, Judy | C18: Friend | D18: Close | E18: 14 Josiah Way | J18: USA | K18: Needs Confirmation | V18: 2024
A19: Craig & Helaina | B19: Craig, Helaina | C19: Friend | D19: Close | J19: USA | K19: Needs Lookup | V19: 2024
A20: Kevin P. | B20: Kevin P. | C20: Friend | D20: Casual | J20: USA | K20: Needs Lookup | V20: 2024
A21: Dave P. | B21: Dave P. | C21: Professional | D21: Casual | E21: 521 Mount Hope St | F21: Suite 300 | H21: MA | J21: USA | K21: Needs Confirmation | V21: 2024
A22: Jake Eid | B22: Jake Eid | C22: Friend | D22: Close | J22: USA | K22: Needs Lookup | V22: 2024
A23: Nico & Sarah | B23: Nico, Sarah | C23: Friend | D23: Close | J23: USA | K23: Needs Lookup | V23: 2024
A24: Tim & Lindsay | B24: Tim, Lindsay | C24: Friend | D24: Close | J24: USA | K24: Needs Lookup | V24: 2024
A25: Tucker & Haley | B25: Tucker, Haley | C25: Friend | D25: Close | E25: 4208 San Rocco Ct | G25: North Las Vegas | H25: NV | J25: USA | K25: Verified | V25: 2024
A26: Kyle & Lily | B26: Kyle, Lily | C26: Friend | D26: Close | E26: 2472 Aelbourne Dr | G26: San Diego | H26: CA | J26: USA | K26: Verified | V26: 2024
A27: Meru | B27: Meru | C27: Friend | D27: Casual | J27: USA | K27: Needs Lookup | V27: 2024
A28: Melissa H | B28: Melissa H | C28: Friend | D28: Casual | J28: USA | K28: Needs Lookup | V28: 2024
A29: Robert | B29: Robert | C29: Friend | D29: Casual | F29: Apt 204 | J29: USA | K29: Needs Lookup | V29: 2024
A30: Kevin & Danielle | B30: Kevin, Danielle | C30: Friend | D30: Close | J30: USA | K30: Needs Lookup | V30: 2024
A31: Joel & Kathryn | B31: Joel, Kathryn | C31: Friend | D31: Close | F31: Apt 205 | J31: USA | K31: Needs Lookup | V31: 2024
A32: Michele (Avila) | B32: Michele | C32: Friend | D32: Close | E32: Avila | J32: USA | K32: Needs Lookup | V32: 2024
A33: Monica & Shell (Avila) | B33: Monica, Shell | C33: Friend | D33: Close | E33: Avila | J33: USA | K33: Needs Lookup | V33: 2024
A34: Lina (Avila) | B34: Lina | C34: Friend | D34: Close | E34: Avila | J34: USA | K34: Needs Lookup | V34: 2024
A35: Angad & Lauren | B35: Angad, Lauren | C35: Friend | D35: Close | E35: 522 Tamarind Way | F35: Unit D | G35: West Covina | H35: CA | J35: USA | K35: Verified | V35: 2024
A36: Grachel | B36: Grachel | C36: Friend | D36: Casual | J36: USA | K36: Needs Lookup | V36: 2024
A37: Katie | B37: Katie | C37: Friend | D37: Close | E37: 5442 E Ebell St | G37: Long Beach | H37: CA | J37: USA | K37: Verified | V37: 2024
A38: Guy & Cynthia | B38: Guy, Cynthia | C38: Friend | D38: Close | E38: 243 Islington Rd | G38: Auburndale | H38: MA | J38: USA | K38: Verified | V38: 2024
A39: Mel Fish | B39: Mel Fish | C39: Friend | D39: Casual | J39: USA | K39: Needs Lookup | V39: 2024
A40: Dan & Viktoria | B40: Dan, Viktoria | C40: Friend | D40: Close | J40: USA | K40: Needs Lookup | V40: 2024

Sheet Annual Budget
A2: INCOME & ALLOCATION
A3: Annual Gross Salary
A4: Relationship Budget % | B4: 5%
A5: Total Relationship Budget | B5: =B3*B4 -> 0
A7: CARD SENDING COSTS
A8: Cards to Send (qty) | B8: =COUNTA(Contacts!A2:A200) -> 39
A9: Photo Cards (cost each) | B9: 2.5
A10: Standard Cards (cost each) | B10: 1.5
A11: Photo Card Qty
A12: Standard Card Qty
A13: Stamps (Forever @ $0.73) | B13: 0.73
A14: Return Address Labels (roll) | B14: 15
A15: Total Card Costs | B15: =B11*B9+B12*B10+(B8*B13)+B14 -> 43.47
A17: GIFT BUDGET BY TIER
A18: Tier A ($100+) - Qty | B18: =COUNTIF(Contacts!AB:AB,"A ($100+)") -> 0
A19: Tier A - Budget Each | B19: 100
A20: Tier A - Subtotal | B20: =B18*B19 -> 0
A21: Tier B ($50-100) - Qty | B21: =COUNTIF(Contacts!AB:AB,"B ($50-100)") -> 0
A22: Tier B - Budget Each | B22: 75
A23: Tier B - Subtotal | B23: =B21*B22 -> 0
A24: Tier C ($25-50) - Qty | B24: =COUNTIF(Contacts!AB:AB,"C ($25-50)") -> 0
A25: Tier C - Budget Each | B25: 37.5
A26: Tier C - Subtotal | B26: =B24*B25 -> 0
A27: Tier D (<$25) - Qty | B27: =COUNTIF(Contacts!AB:AB,"D (<$25)") -> 0
A28: Tier D - Budget Each | B28: 20
A29: Tier D - Subtotal | B29: =B27*B28 -> 0
A30: Total Gift Budget | B30: =B20+B23+B26+B29 -> 0
A32: OTHER RELATIONSHIP COSTS
A33: Hosting/Entertaining
A34: Travel for Relationships
A35: Spontaneous Generosity Buffer
A36: Total Other | B36: =SUM(B33:B35) -> 0
A38: SUMMARY
A39: Total Planned Spend | B39: =B15+B30+B36 -> 43.47
A40: Budget Remaining | B40: =B5-B38 -> 0
A41: Budget Utilization % | B41: =IF(B5>0,B38/B5,0) -> 0

Sheet Inventory
A1: Item | B1: Category | C1: Qty On Hand | D1: Reorder Point | E1: Unit Cost | F1: Total Value | G1: Supplier | H1: Last Ordered | I1: Notes
A2: Photo Cards (pack of 25) | B2: Cards | D2: 50 | E2: 25 | F2: =C2*E2 -> 0 | G2: Shutterfly | I2: Order by Nov 15
A3: Standard Cards (box of 20) | B3: Cards | D3: 40 | E3: 15 | F3: =C3*E3 -> 0 | G3: Target
A4: Forever Stamps (book of 20) | B4: Postage | D4: 60 | E4: 14.6 | F4: =C4*E4 -> 0 | G4: USPS | I4: Price may increase
A5: Return Address Labels (roll) | B5: Labels | D5: 2 | E5: 15 | F5: =C5*E5 -> 0 | G5: Brother | I5: DK-2205 continuous
A6: Address Labels 2.4" B/R | B6: Labels | D6: 2 | E6: 25 | F6: =C6*E6 -> 0 | G6: Brother | I6: For QL-820NWB
A7: Gift Wrap - Roll | B7: Wrapping | D7: 5 | E7: 8 | F7: =C7*E7 -> 0 | G7: Target
A8: Gift Bags - Small | B8: Wrapping | D8: 10 | E8: 1.5 | F8: =C8*E8 -> 0 | G8: Dollar Tree
A9: Gift Bags - Medium | B9: Wrapping | D9: 10 | E9: 2 | F9: =C9*E9 -> 0 | G9: Dollar Tree
A10: Gift Bags - Large | B10: Wrapping | D10: 5 | E10: 3 | F10: =C10*E10 -> 0 | G10: Dollar Tree
A11: Tissue Paper (pack) | B11: Wrapping | D11: 3 | E11: 3 | F11: =C11*E11 -> 0 | G11: Dollar Tree
A12: Ribbon (spool) | B12: Wrapping | D12: 3 | E12: 5 | F12: =C12*E12 -> 0 | G12: Michaels
A13: Gift Tags (pack of 50) | B13: Wrapping | D13: 100 | E13: 5 | F13: =C13*E13 -> 0 | G13: Amazon
A14: Thank You Cards (box) | B14: Cards | D14: 20 | E14: 12 | F14: =C14*E14 -> 0 | G14: Target | I14: For post-holiday
A15: Envelopes (A7) | B15: Cards | D15: 50 | E15: 10 | F15: =C15*E15 -> 0 | G15: Amazon | I15: For photo cards
E17: Total Inventory Value: | F17: =SUM(F2:F15) -> 0

Sheet Spending History
A1: Year | B1: Cards Sent | C1: Card Cost | D1: Gifts Given | E1: Gift Spend | F1: Gifts Received | G1: Est Value Received | H1: Net Flow | I1: Total Spend | J1: Notes
A2: 2024 | H2: =G2-E2 -> 0 | I2: =C2+E2 -> 0
A3: 2025 | H3: =G3-E3 -> 0 | I3: =C3+E3 -> 0
A4: 2026 | H4: =G4-E4 -> 0 | I4: =C4+E4 -> 0
A5: 2027 | H5: =G5-E5 -> 0 | I5: =C5+E5 -> 0
A6: 2028 | H6: =G6-E6 -> 0 | I6: =C6+E6 -> 0
A7: 2029 | H7: =G7-E7 -> 0 | I7: =C7+E7 -> 0
A8: 2030 | H8: =G8-E8 -> 0 | I8: =C8+E8 -> 0
A9: 2031 | H9: =G9-E9 -> 0 | I9: =C9+E9 -> 0
A10: 2032 | H10: =G10-E10 -> 0 | I10: =C10+E10 -> 0
A11: 2033 | H11: =G11-E11 -> 0 | I11: =C11+E11 -> 0
A12: 2034 | H12: =G12-E12 -> 0 | I12: =C12+E12 -> 0

Sheet Dashboard
A1: 🎄 CHRISTMAS CARD CIRCUIT DASHBOARD
A3: CONTACT METRICS
A4: Total Contacts | B4: =COUNTA(Contacts!A2:A200) -> 39 | C4: people
A5: Addresses Verified | B5: =COUNTIF(Contacts!K:K,"Verified") -> 10 | C5: ready to print
A6: Addresses Needing Lookup | B6: =COUNTIF(Contacts!K:K,"Needs Lookup") -> 23 | C6: ⚠️ action needed
A7: Addresses Needing Confirmation | B7: =COUNTIF(Contacts!K:K,"Needs Confirmation") -> 6 | C7: to verify
A9: RELATIONSHIP BREAKDOWN
A10: Family | B10: =COUNTIF(Contacts!C:C,"Family") -> 13
A11: Friends | B11: =COUNTIF(Contacts!C:C,"Friend") -> 25
A12: Professional | B12: =COUNTIF(Contacts!C:C,"Professional") -> 1
A13: Inner Circle | B13: =COUNTIF(Contacts!D:D,"Inner Circle") -> 5
A14: Close | B14: =COUNTIF(Contacts!D:D,"Close") -> 27
A16: 2024 CARD STATUS
A17: Cards Sent | B17: =COUNTIF(Contacts!X:X,TRUE())+COUNTIF(Contacts!X:X,"Yes")+COUNTIF(Contacts!X:X,"x") -> 0
A18: Cards Remaining | B18: =B4-B17 -> 39
A19: Response Rate | B19: =IF(B17>0,COUNTIF(Contacts!Y:Y,"Received Card")/B17,0) -> 0
A21: BUDGET STATUS
A22: Total Budget | B22: ='Annual Budget'!B5 -> 0
A23: Planned Spend | B23: ='Annual Budget'!B38 -> 0
A24: Budget Remaining | B24: ='Annual Budget'!B39 -> 43.47
A26: INVENTORY ALERTS
A27: Total Inventory Value | B27: =Inventory!F17 -> 0

Sheet Addresses Needed
A1: Household Name | B1: Individual Names | C1: Relationship | D1: Current Address Info | E1: Status | F1: Notes
A2: Filter Contacts tab by Address Status = 'Needs Lookup'
